pg_query/__main__.py
pg_query/__init__.py
pg_query/keywords.py
pg_query/parser.cpython-34m.so
pg_query/error.py
pg_query/printer.py
pg_query/node.py
pg_query/enums/pg_class.py
pg_query/enums/__init__.py
pg_query/enums/primnodes.py
pg_query/enums/nodes.py
pg_query/enums/parsenodes.py
pg_query/enums/lockoptions.py
pg_query/printers/sfuncs.py
pg_query/printers/dml.py
pg_query/printers/__init__.py
pg_query/printers/ddl.py
pg_query-0.28.dist-info/WHEEL
pg_query-0.28.dist-info/top_level.txt
pg_query-0.28.dist-info/METADATA
pg_query-0.28.dist-info/RECORD
pg_query-0.28.dist-info/entry_points.txt
