Metadata-Version: 1.1
Name: pg_query
Version: 0.28
Summary: Pythonic wrapper around libpg_query and PostgreSQL prettifier
Home-page: https://github.com/lelit/pg_query
Author: Lele Gaifax
Author-email: lele@metapensiero.it
License: GPLv3+
Keywords: postgresql parser sql prettifier
Platform: UNKNOWN
Classifier: Development Status :: 3 - Alpha
Classifier: Intended Audience :: Developers
Classifier: License :: OSI Approved :: GNU General Public License v3 or later (GPLv3+)
Classifier: Programming Language :: Python
Classifier: Programming Language :: Python :: 3
Classifier: Programming Language :: Python :: 3 :: Only
Classifier: Programming Language :: Python :: 3.4
Classifier: Programming Language :: Python :: 3.5
Classifier: Programming Language :: Python :: 3.6
Classifier: Programming Language :: SQL
Classifier: Topic :: Database
Classifier: Topic :: Utilities
